{
  "currentConfig": {
    "guid": "7b364c2d-b555-4095-9fc2-e7594dc0c4db",
    "name": "test2",
    "nameUi": "test1",
    "lastUpdated": "2023-12-10T21:32:40.816449400Z",
    "sortingValue": "146311674827118551",
    "isNeedCurrentUpdate": true,
    "groupConfigLinks": {
      "guid": "bf2b27e8-6d29-4db2-b9d3-6672a43d2c93",
      "name": "BaseConfigs",
      "sortingValue": "59235912622939962"
    },
    "model": {
      "guid": "decd0b15-05ff-40c9-a28b-dd22935060c6",
      "name": "Model",
      "sortingValue": "1266818643803827315",
      "nameUi": "Model",
      "compositeNameMaxLength": 100,
      "isUseCompositeNames": true,
      "isUseGroupPrefix": true,
      "pKeyGuid": "36d87673-f17e-45fe-a337-a37ec84918c4",
      "pKeyName": "Id",
      "recordVersionFieldGuid": "6e361b29-6e92-4f9e-a87c-09692ae143a6",
      "recordVersionFieldName": "ReCoRdVeRsIoN",
      "recordVersionFieldType": "VER_INT",
      "propertyCodeName": "Code",
      "useCodeProperty": true,
      "propertyNameName": "Name",
      "useNameProperty": true,
      "propertyDescriptionName": "Description",
      "propertyIsFolderName": "IsFolder",
      "propertyDocDateName": "DocDate",
      "useDocDateProperty": true,
      "propertyDocNumberName": "DocNumber",
      "useDocNumberProperty": true,
      "groupConstantGroups": {
        "guid": "32492945-817f-4183-ac42-32c0b1b18b7a",
        "name": "Constants",
        "sortingValue": "8136298302896683707",
        "nameUi": "Constants",
        "prefixForDbTables": "Cnst"
      },
      "groupEnumerations": {
        "guid": "1bb14dd2-5b30-47c8-b25a-8d1b96b15438",
        "name": "Enumerations",
        "nameUi": "Enumerations",
        "sortingValue": "9298730994942060253"
      },
      "groupCatalogs": {
        "guid": "7134fd95-5366-4599-9f91-691e08f8687a",
        "name": "Catalogs",
        "nameUi": "Catalogs",
        "prefixForDbTables": "Ctlg",
        "shortIdTypeForCacheKey": "c",
        "sortingValue": "10440341194287976358",
        "useCodePropertyInSeparateTree": true,
        "useNamePropertyInSeparateTree": true
      },
      "groupDocuments": {
        "guid": "7dc3ab8d-92ec-453a-9d20-e07faf1a9593",
        "name": "Documents",
        "sortingValue": "11599832935996694584",
        "nameUi": "Documents",
        "prefixForDbTables": "Doc",
        "groupSharedProperties": {
          "guid": "613dd241-6147-4682-9d98-b38a327dd4c5",
          "name": "Default Properties",
          "nameUi": "Default Properties",
          "sortingValue": "2375169941565728410"
        },
        "groupListDocuments": {
          "guid": "6154ba0c-499e-4755-bd32-92b315ebce81",
          "name": "Documents",
          "nameUi": "Documents",
          "shortIdTypeForCacheKey": "d",
          "sortingValue": "3529382403748765752"
        },
        "mondayBeforeFirstDocDate": "1000-01-06T00:00:00Z"
      },
      "groupJournals": {
        "guid": "99755eac-acc9-49f1-af65-695a8376d2cd",
        "name": "Journals",
        "nameUi": "Journals",
        "sortingValue": "15087511898170793690"
      },
      "groupCommon": {
        "guid": "51dd8460-b2e8-460e-ad6d-482e213a48c4",
        "name": "Common Group",
        "nameUi": "Common Group",
        "sortingValue": "6983372704246320642",
        "groupRoles": {
          "guid": "3c9c91ee-dd82-4c00-bef5-55f89190c267",
          "name": "Roles",
          "nameUi": "Roles",
          "sortingValue": "7055497206495867671"
        },
        "groupViewForms": {
          "guid": "73757de1-3857-4564-b24b-e013465402f8",
          "name": "Views",
          "nameUi": "Views",
          "sortingValue": "156399867323297696"
        },
        "groupListSequences": {
          "guid": "6d3a31ec-930b-4fa2-8660-b0f34c775ae9",
          "name": "Sequences",
          "sortingValue": "1294417697512652434",
          "nameUi": "Sequences"
        }
      },
      "groupListRegisters": {
        "guid": "8fb63e96-85f3-4bcc-a38c-ef9b316ba11d",
        "name": "Registers",
        "nameUi": "Registers",
        "sortingValue": "13971709436179126794",
        "prefixForDbTables": "Reg",
        "shortIdTypeForCacheKey": "rg",
        "propertyRegGuidGuid": "4970f369-f843-40e4-87f6-de10bc9fbf66",
        "propertyDocDateGuid": "2a35c41d-61fa-446f-8159-be1fe66f13c4",
        "propertyDocDateSequenceGuid": "a4068304-1fd4-4a46-832c-e67764425eb6",
        "propertyVersionGuid": "cfbec7b8-ecc2-47be-a95d-525e5e54bd4a"
      },
      "groupRelations": {
        "guid": "a3b2ea51-cad9-4660-bfc6-e57dfcbe6057",
        "name": "Many To Many",
        "sortingValue": "12794251194628471522",
        "nameUi": "Many To Many",
        "groupListCatalogsRelations": {
          "guid": "3ffac790-dd2d-46ee-99a6-34fbb0a8179e",
          "name": "Catalogs",
          "nameUi": "Catalogs",
          "prefixForDbTables": "CtlgManyToMany",
          "shortIdTypeForCacheKey": "m",
          "sortingValue": "2369890662040047526"
        },
        "groupListDocumentsRelations": {
          "guid": "d1699897-7e5e-4a59-80b9-62ebb72f6383",
          "name": "Documents",
          "nameUi": "Documents",
          "prefixForDbTables": "DocManyToMany",
          "shortIdTypeForCacheKey": "m",
          "sortingValue": "3529382403748765752"
        }
      }
    },
    "groupPlugins": {
      "guid": "1a45ba29-807d-40a1-96a2-0c0af971b048",
      "name": "Plugins",
      "listPlugins": [
        {
          "guid": "3829EEAB-71BB-4BE2-91E6-70872B6FB85C",
          "version": "0.1",
          "name": "Blazor",
          "description": "Blazor code generation plugin",
          "sortingValue": "60604291650866822",
          "listGenerators": [
            {
              "guid": "1E35FCDB-6425-4C66-B047-6882738AF552",
              "name": "Repository",
              "description": "DB repository code generation",
              "sortingValue": "136683562068488024"
            }
          ],
          "isNew": true
        },
        {
          "guid": "052C7318-3D73-4605-B1AE-749FC7E10412",
          "version": "0.1",
          "name": "DbRepository",
          "description": "vSharpStudio plugin. DB access layer repository code",
          "sortingValue": "68979563992098251",
          "listGenerators": [
            {
              "guid": "E59B393E-AF34-4438-977F-7BF120E28A0C",
              "name": "Repository",
              "description": "Db Access Layer",
              "sortingValue": "136683562068488024"
            }
          ],
          "isNew": true
        },
        {
          "guid": "EDE860F8-2E9B-4E17-8A80-2D52879D15AB",
          "version": "0.1",
          "name": "gRPC",
          "description": "vSharpStudio plugin. gRPC service code",
          "sortingValue": "85477421625570264",
          "listGenerators": [
            {
              "guid": "32B15714-E660-4E29-9291-D647A1774149",
              "name": "gRPC service",
              "description": "gRPC services server code, client code, protobuf defenitions",
              "sortingValue": "85477423666120240"
            }
          ],
          "isNew": true
        },
        {
          "guid": "C94175E4-E8F4-4A84-871B-6994199A2076",
          "version": "0.1",
          "name": "MsSql",
          "description": "vSharpStudio plugin. Database design support for MS SQL",
          "sortingValue": "114470812530495058",
          "listGenerators": [
            {
              "guid": "0D85CF93-9134-45C6-B3B9-6BFAF4A12183",
              "name": "Design",
              "description": "DB structure creation and migration",
              "sortingValue": "69373318202209198"
            }
          ],
          "isNew": true
        },
        {
          "guid": "3A29FC48-3892-498A-AE36-CB0C9916C6C9",
          "version": "0.1",
          "name": "PostgreSql",
          "description": "vSharpStudio plugin. Database design support for PostgreSql",
          "sortingValue": "128376992626817576",
          "listGenerators": [
            {
              "guid": "C641770F-CBA5-4FC5-8068-A21C00D6E492",
              "name": "Design",
              "description": "DB structure creation and migration",
              "sortingValue": "69373318202209198"
            }
          ],
          "isNew": true
        },
        {
          "guid": "ED93228B-8D8E-456C-9688-37EEB1B2D835",
          "version": "0.1",
          "name": "Sample",
          "description": "vSharpStudio plugin with several generators",
          "sortingValue": "140961838680249462",
          "listGenerators": [
            {
              "guid": "08744482-BE03-464B-81AB-DD482AB66103",
              "name": "AbstractDbSchema",
              "description": "Description Abstract Db Schema",
              "sortingValue": "54558751463641263"
            },
            {
              "guid": "7C2902AF-DF34-46FC-8911-A48EE7F9B2B0",
              "name": "DbAccess",
              "description": "Description Db Access Layer",
              "sortingValue": "68919627930208948"
            }
          ],
          "isNew": true
        },
        {
          "guid": "D535B939-6A33-4B96-B64C-F8FB78FD9F94",
          "version": "0.1",
          "name": "Sample2",
          "description": "vSharpStudio plugin with one generators",
          "sortingValue": "140961838685871945",
          "listGenerators": [
            {
              "guid": "8876C5ED-8375-403B-A792-D05019BD89E0",
              "name": "DbAccess2",
              "description": "Description Db Access Layer",
              "sortingValue": "68919627930213055"
            }
          ],
          "isNew": true
        },
        {
          "guid": "16376EA9-1FBD-4945-8160-BCCC3262128B",
          "version": "0.1",
          "name": "Sqlite",
          "description": "vSharpStudio plugin. Database design for Sqlite support",
          "sortingValue": "143037070040188114",
          "listGenerators": [
            {
              "guid": "553A6E65-FF70-4CEA-B7B4-53DD1DC55F0E",
              "name": "Design",
              "description": "DB structure creation and migration",
              "sortingValue": "69373318202209198"
            }
          ],
          "isNew": true
        }
      ],
      "sortingValue": "10504286444592368772"
    },
    "groupAppSolutions": {
      "guid": "773234b2-63bb-48b0-9be6-60a817a8da6c",
      "name": "User Applications",
      "sortingValue": "11682105398164708376"
    }
  }
}